passagemath_gap_pkg_normalizinterface-10.6.43.dist-info/RECORD
passagemath_gap_pkg_normalizinterface-10.6.43.dist-info/METADATA.bak
passagemath_gap_pkg_normalizinterface-10.6.43.dist-info/WHEEL
passagemath_gap_pkg_normalizinterface-10.6.43.dist-info/top_level.txt
passagemath_gap_pkg_normalizinterface-10.6.43.dist-info/METADATA
gap/pkg/normalizinterface/PackageInfo.g
gap/pkg/normalizinterface/LICENSE
gap/pkg/normalizinterface/CHANGES
gap/pkg/normalizinterface/README.md
gap/pkg/normalizinterface/makedoc.g
gap/pkg/normalizinterface/init.g
gap/pkg/normalizinterface/read.g
gap/pkg/normalizinterface/bin/x86_64-apple-darwin24-default64-kv10/NormalizInterface.so
gap/pkg/normalizinterface/etc/generate_cone_property_wrappers.g
gap/pkg/normalizinterface/etc/download.sh
gap/pkg/normalizinterface/examples/dual_mode.g
gap/pkg/normalizinterface/examples/demo.g
gap/pkg/normalizinterface/examples/5x5.g
gap/pkg/normalizinterface/examples/magic_square.g
gap/pkg/normalizinterface/examples/docs.g
gap/pkg/normalizinterface/lib/normaliz.gi
gap/pkg/normalizinterface/lib/cone_property_wrappers.gi
gap/pkg/normalizinterface/lib/normaliz.gd
gap/pkg/normalizinterface/lib/cone_property_wrappers.gd
gap/pkg/normalizinterface/tst/cube-incidence.tst
gap/pkg/normalizinterface/tst/descent.tst
gap/pkg/normalizinterface/tst/rp2poly.tst
gap/pkg/normalizinterface/tst/project.tst
gap/pkg/normalizinterface/tst/gorenstein.tst
gap/pkg/normalizinterface/tst/bugfix.tst
gap/pkg/normalizinterface/tst/normalizinterface02.tst
gap/pkg/normalizinterface/tst/InhomIneq.tst
gap/pkg/normalizinterface/tst/fractions.tst
gap/pkg/normalizinterface/tst/dual.tst
gap/pkg/normalizinterface/tst/normalizinterface01.tst
gap/pkg/normalizinterface/tst/verticesfloat.tst
gap/pkg/normalizinterface/tst/rproj2.tst
gap/pkg/normalizinterface/tst/rational.tst
gap/pkg/normalizinterface/tst/conversion.tst
gap/pkg/normalizinterface/tst/rees.tst
gap/pkg/normalizinterface/tst/testall.g
passagemath_gap_pkg_normalizinterface/__init__.py
passagemath_gap_pkg_normalizinterface/.dylibs/libgmpxx.4.dylib
passagemath_gap_pkg_normalizinterface/.dylibs/libeantic.3.dylib
passagemath_gap_pkg_normalizinterface/.dylibs/libnormaliz.3.dylib
passagemath_gap_pkg_normalizinterface/.dylibs/libflint.22.0.dylib
